dialback/__init__.py
dialback/dialback.py
dialback/exceptions.py
python_dialback-0.1.1.dist-info/DESCRIPTION.rst
python_dialback-0.1.1.dist-info/METADATA
python_dialback-0.1.1.dist-info/metadata.json
python_dialback-0.1.1.dist-info/RECORD
python_dialback-0.1.1.dist-info/top_level.txt
python_dialback-0.1.1.dist-info/WHEEL
